{
  "gitSyncId": "68361b0199ac85635af1fb52_410af2d4-aee6-4bf7-b713-22fe167305a2",
  "id": "VerTodasLasTiendas_UsuariosBatch.actualizarPorCodigoUsuario",
  "pluginId": "js-plugin",
  "pluginType": "JS",
  "unpublishedAction": {
    "actionConfiguration": {
      "encodeParamsToggle": true,
      "jsArguments": [
        {
          "name": "codigo_usuario"
        },
        {
          "name": "nuevaPassword"
        }
      ],
      "paginationType": "NONE",
      "timeoutInMillisecond": 10000
    },
    "collectionId": "VerTodasLasTiendas_UsuariosBatch",
    "confirmBeforeExecute": false,
    "datasource": {
      "isAutoGenerated": false,
      "name": "UNUSED_DATASOURCE",
      "pluginId": "js-plugin"
    },
    "dynamicBindingPathList": [
      {
        "key": "body"
      }
    ],
    "fullyQualifiedName": "UsuariosBatch.actualizarPorCodigoUsuario",
    "name": "actualizarPorCodigoUsuario",
    "pageId": "VerTodasLasTiendas",
    "runBehaviour": "MANUAL",
    "userSetOnLoad": false
  }
}